lotide_luna/__init__.py
lotide_luna/admin.py
lotide_luna/apps.py
lotide_luna/context_processors.py
lotide_luna/models.py
lotide_luna/tests.py
lotide_luna/urls.py
lotide_luna/utils.py
lotide_luna/locale/.gitignore
lotide_luna/locale/LICENSE
lotide_luna/locale/vi/LC_MESSAGES/django.po
lotide_luna/migrations/__init__.py
lotide_luna/static/about.txt
lotide_luna/static/android-chrome-192x192.png
lotide_luna/static/android-chrome-512x512.png
lotide_luna/static/apple-touch-icon.png
lotide_luna/static/favicon-16x16.png
lotide_luna/static/favicon-32x32.png
lotide_luna/static/favicon.ico
lotide_luna/static/luna-dark.css
lotide_luna/static/luna-light.css
lotide_luna/static/luna-system.css
lotide_luna/static/site.webmanifest
lotide_luna/static/style.css
lotide_luna/templates/base.html
lotide_luna/templates/comment.html
lotide_luna/templates/communities.html
lotide_luna/templates/community.html
lotide_luna/templates/index.html
lotide_luna/templates/login.html
lotide_luna/templates/new-post.html
lotide_luna/templates/post.html
lotide_luna/templates/settings.html
lotide_luna/templates/timeline.html
lotide_luna/templates/user.html
lotide_luna/templates/error/no_cookie.html
lotide_luna/templatetags/__init__.py
lotide_luna/templatetags/datetime_filter.py
lotide_luna/views/__init__.py
lotide_luna/views/auth.py
lotide_luna/views/comment.py
lotide_luna/views/community.py
lotide_luna/views/post.py
lotide_luna/views/settings.py
lotide_luna/views/timeline.py
lotide_luna/views/user.py
lotide_luna-0.7.1.dist-info/COPYING
lotide_luna-0.7.1.dist-info/WHEEL
lotide_luna-0.7.1.dist-info/METADATA
lotide_luna-0.7.1.dist-info/RECORD
